{"lsp_signature.nvim": {"commit": "e4f7dad"}, "cmp-nvim-lsp": {"commit": "ebdfc20"}, "nvim-toggleterm.lua": {"commit": "9f969e7"}, "nvim-dap": {"commit": "e6d7ba5"}, "nvim-treesitter-context": {"commit": "b7d7aba"}, "nvim-tree.lua": {"commit": "1831417"}, "cmp-emoji": {"commit": "19075c3"}, "packer.nvim": {"commit": "4dedd3b"}, "nvim-notify": {"commit": "da10302"}, "fidget.nvim": {"commit": "d47f2bb"}, "nvim-lspconfig": {"commit": "7d5a6dc"}, "registers.nvim": {"commit": "c66458f"}, "nvim-bqf": {"commit": "7d3630f"}, "nvim-dap-ui": {"commit": "45805d6"}, "plenary.nvim": {"commit": "0d66015"}, "gitsigns.nvim": {"commit": "2a10723"}, "indent-blankline.nvim": {"commit": "ebedbed"}, "nvim-lightbulb": {"commit": "29ca814"}, "nvim-cmp": {"commit": "272cbdc"}, "copilot.vim": {"commit": "47eb231"}, "nvim-treesitter": {"commit": "cd4d802"}, "vim-searchindex": {"commit": "b0788c8"}, "vim-visual-multi": {"commit": "4fcd379"}, "lsp_extensions.nvim": {"commit": "4011f4a"}, "telescope.nvim": {"commit": "cf2d6d3"}, "cmp-nvim-lsp-document-symbol": {"commit": "c3f0086"}, "gruvbox-material": {"commit": "b8b63c8"}, "zoomwintab.vim": {"commit": "7a354f3"}, "lualine.nvim": {"commit": "e9b935c"}, "vim-polyglot": {"commit": "83422e0a"}, "cmp-nvim-lua": {"commit": "d276254"}, "cmp-cmdline": {"commit": "f4beb74"}, "cmp-path": {"commit": "466b6b8"}, "cmp-buffer": {"commit": "d66c4c2"}}
